{
  "fear_greed_value": 14,
  "fear_greed_label": "Extreme Fear",
  "btc_dominance": 57.06,
  "funding_rate": -0.002274,
  "funding_symbol": "BTCUSDT",
  "macro_bias": "BEARISH",
  "block_longs": false,
  "block_shorts": false,
  "reason": "NASDAQ Bajista: Risk-Off",
  "dxy_trend": "BEARISH",
  "dxy_price": 98.93,
  "nasdaq_trend": "BEARISH",
  "nasdaq_change_pct": -0.42,
  "risk_appetite": "RISK_OFF",
  "news_sentiment": 0.5,
  "active_event": "",
  "last_updated": 1775748361.590616,
  "is_stale": false
}